[
    {
        "Name": "John",
        "DOB": "1990-05-15",
        "Height": 175,
        "City": "Mumbai",
        "State": "Maharashtra"
    },
    {
        "Name": "Alice",
        "DOB": "1985-08-20",
        "Height": 160,
        "City": "Delhi",
        "State": "Delhi"
    },
    {
        "Name": "Bob",
        "DOB": "1992-03-10",
        "Height": 180,
        "City": "Bangalore",
        "State": "Karnataka"
    },
    {
        "Name": "Emily",
        "DOB": "1988-12-25",
        "Height": 168,
        "City": "Kolkata",
        "State": "West Bengal"
    },
    {
        "Name": "Mike",
        "DOB": "1995-06-30",
        "Height": 172,
        "City": "Chennai",
        "State": "Tamil Nadu"
    }
]
